acuity_cli/__init__.py
acuity_cli/__main__.py
acuity_cli/cli.py
acuity_cli/client.py
acuity_cli/config.py
acuity_cli/errors.py
acuity_cli/filters.py
acuity_cli/formatters.py
acuity_cli/validators.py
acuity_cli/commands/__init__.py
acuity_cli/commands/appointments.py
acuity_cli/commands/availability.py
acuity_cli/commands/calendars.py
acuity_cli/commands/clients.py
acuity_cli/commands/config_cmd.py
acuity_cli/commands/types.py
acuity_cli/commands/update.py
dc_acuity_cli-1.4.2.dist-info/METADATA
dc_acuity_cli-1.4.2.dist-info/WHEEL
dc_acuity_cli-1.4.2.dist-info/entry_points.txt
dc_acuity_cli-1.4.2.dist-info/RECORD
