Metadata-Version: 2.4
Name: dc-acuity-cli
Version: 1.4.2
Summary: CLI for managing Acuity Scheduling appointments, clients, and availability
Project-URL: Documentation, https://github.com/real-news-pr/acuity-schedule-manager#readme
Project-URL: Issues, https://github.com/real-news-pr/acuity-schedule-manager/issues
Project-URL: Source, https://github.com/real-news-pr/acuity-schedule-manager
Author: Real News PR
License-Expression: MIT
Keywords: acuity,appointments,cli,scheduling
Classifier: Development Status :: 4 - Beta
Classifier: Environment :: Console
Classifier: Intended Audience :: Developers
Classifier: License :: OSI Approved :: MIT License
Classifier: Operating System :: OS Independent
Classifier: Programming Language :: Python :: 3
Classifier: Programming Language :: Python :: 3.10
Classifier: Programming Language :: Python :: 3.11
Classifier: Programming Language :: Python :: 3.12
Classifier: Topic :: Office/Business :: Scheduling
Requires-Python: >=3.10
Requires-Dist: python-dotenv>=1.0.0
Requires-Dist: requests>=2.28.0
Provides-Extra: dev
Requires-Dist: mypy>=1.0.0; extra == 'dev'
Requires-Dist: pytest-mock>=3.10.0; extra == 'dev'
Requires-Dist: pytest>=7.0.0; extra == 'dev'
Requires-Dist: ruff>=0.1.0; extra == 'dev'
Requires-Dist: types-requests>=2.28.0; extra == 'dev'
